data_tamer/__init__.py
data_tamer/batch.py
data_tamer/core.py
data_tamer/prompt.py
data_tamer/schema.py
data_tamer/types.py
data_tamer-0.1.5.dist-info/METADATA
data_tamer-0.1.5.dist-info/WHEEL
data_tamer-0.1.5.dist-info/top_level.txt
data_tamer-0.1.5.dist-info/RECORD
