Metadata-Version: 2.4
Name: data-tamer
Version: 0.1.5
Summary: Python port of data-tamer using LiteLLM for structured outputs and batching
Author: Sebastian Lewis
License-Expression: MIT
Project-URL: Homepage, https://github.com/seb-lewis/data-tamer
Project-URL: Repository, https://github.com/seb-lewis/data-tamer
Project-URL: Issues, https://github.com/seb-lewis/data-tamer/issues
Keywords: llm,structured-output,pydantic,jsonschema,batching,litellm
Classifier: Development Status :: 3 - Alpha
Classifier: Intended Audience :: Developers
Classifier: Topic :: Software Development :: Libraries
Classifier: Programming Language :: Python :: 3
Classifier: Programming Language :: Python :: 3 :: Only
Classifier: Programming Language :: Python :: 3.9
Classifier: Programming Language :: Python :: 3.10
Classifier: Programming Language :: Python :: 3.11
Classifier: Programming Language :: Python :: 3.12
Classifier: Operating System :: OS Independent
Requires-Python: >=3.9
Requires-Dist: litellm<1.41.0,>=1.30.0
Requires-Dist: pydantic>=2.0
Requires-Dist: jsonschema>=4.18.0
